better_transformer/__init__.py
better_transformer/models/__init__.py
better_transformer/models/attention.py
better_transformer/models/base.py
better_transformer/models/decoder_models.py
better_transformer/models/encoder_models.py
better_transformer/transformation.py
better_transformer/utils/__init__.py
better_transformer/utils/constant.py
better_transformer/utils/doc.py
better_transformer/utils/dummy_bettertransformer_objects.py
better_transformer/utils/dummy_diffusers_objects.py
better_transformer/utils/file_utils.py
better_transformer/utils/import_utils.py
better_transformer/utils/input_generators.py
better_transformer/utils/logging.py
better_transformer/utils/modeling_utils.py
better_transformer/utils/normalized_config.py
better_transformer/utils/preprocessing/__init__.py
better_transformer/utils/preprocessing/base.py
better_transformer/utils/preprocessing/image_classification.py
better_transformer/utils/preprocessing/question_answering.py
better_transformer/utils/preprocessing/task_processors_manager.py
better_transformer/utils/preprocessing/text_classification.py
better_transformer/utils/preprocessing/token_classification.py
better_transformer/utils/runs.py
better_transformer/utils/save_utils.py
better_transformer/utils/testing_utils.py
better_transformer-0.2.0.dist-info/METADATA
better_transformer-0.2.0.dist-info/WHEEL
better_transformer-0.2.0.dist-info/licenses/LICENSE
better_transformer-0.2.0.dist-info/RECORD
