Metadata-Version: 2.4
Name: better-transformer
Version: 0.2.0
Summary: 
License-File: LICENSE
Author: wirthual
Author-email: wirthra@gmail.com
Requires-Python: >=3.9,<3.14
Classifier: Programming Language :: Python :: 3
Classifier: Programming Language :: Python :: 3.9
Classifier: Programming Language :: Python :: 3.10
Classifier: Programming Language :: Python :: 3.11
Classifier: Programming Language :: Python :: 3.12
Classifier: Programming Language :: Python :: 3.13
Requires-Dist: accelerate (>=1.10.1,<2.0.0)
Requires-Dist: optimum (>=1.27.0,<3.0.0)
Requires-Dist: transformers (>=4.51.3,<5.0.0)
